myCalculatorPackage99/__init__.py
myCalculatorPackage99/division/__init__.py
myCalculatorPackage99/division/divide.py
myCalculatorPackage99/multiplication/__init__.py
myCalculatorPackage99/multiplication/multiply.py
myCalculatorPackage99-0.0.1.dist-info/LICENSE.txt
myCalculatorPackage99-0.0.1.dist-info/METADATA
myCalculatorPackage99-0.0.1.dist-info/WHEEL
myCalculatorPackage99-0.0.1.dist-info/top_level.txt
myCalculatorPackage99-0.0.1.dist-info/RECORD
